Workbook
Name Expense_Tracker: 'Clean data'!$A$1:$L$487
Name Slicer_Main_Category: #N/A
Name Slicer_Months__Date: #N/A
Name Slicer_Payment_mode: #N/A

Sheet Dataset
A1: Date | B1: Description | C1: Debit | D1: Credit | E1: Sub-category | F1: Category | G1: Category Type | H1: Month Number | I1: Weekday | J1: Amount
A2: 44200 | B2: Data With Decision | D2: 5000 | E2: Data with Decision | F2: Salary | G2: Income | H2: =MONTH(Dataset!$A2) -> 1 | I2: =WEEKDAY(Dataset!$A2) -> 2 | J2: =Dataset!$D2-Dataset!$C2 -> 5000
A3: 44200 | B3: Drink | C3: 5 | E3: Coffee | F3: Dining Out | G3: Expense | H3: =MONTH(Dataset!$A3) -> 1 | I3: =WEEKDAY(Dataset!$A3) -> 2 | J3: =Dataset!$D3-Dataset!$C3 -> -5
A4: 44201 | B4: Estate Mangement | C4: 900 | E4: Rent | F4: Living Expenses | G4: Expense | H4: =MONTH(Dataset!$A4) -> 1 | I4: =WEEKDAY(Dataset!$A4) -> 3 | J4: =Dataset!$D4-Dataset!$C4 -> -900
A5: 44201 | B5: Financail upgrade | C5: 150 | E5: Cash loan | F5: Transport | G5: Expense | H5: =MONTH(Dataset!$A5) -> 1 | I5: =WEEKDAY(Dataset!$A5) -> 3 | J5: =Dataset!$D5-Dataset!$C5 -> -150
A6: 44201 | B6: Drink | C6: 5 | E6: Coffee | F6: Dining Out | G6: Expense | H6: =MONTH(Dataset!$A6) -> 1 | I6: =WEEKDAY(Dataset!$A6) -> 3 | J6: =Dataset!$D6-Dataset!$C6 -> -5
A7: 44202 | B7: Drink | C7: 5 | E7: Coffee | F7: Dining Out | G7: Expense | H7: =MONTH(Dataset!$A7) -> 1 | I7: =WEEKDAY(Dataset!$A7) -> 4 | J7: =Dataset!$D7-Dataset!$C7 -> -5
A8: 44203 | B8: Drink | C8: 5 | E8: Coffee | F8: Dining Out | G8: Expense | H8: =MONTH(Dataset!$A8) -> 1 | I8: =WEEKDAY(Dataset!$A8) -> 5 | J8: =Dataset!$D8-Dataset!$C8 -> -5
A9: 44204 | B9: Drink | C9: 5 | E9: Coffee | F9: Dining Out | G9: Expense | H9: =MONTH(Dataset!$A9) -> 1 | I9: =WEEKDAY(Dataset!$A9) -> 6 | J9: =Dataset!$D9-Dataset!$C9 -> -5
A10: 44204 | B10: Green's | C10: 155 | E10: Groceries | F10: Living Expenses | G10: Expense | H10: =MONTH(Dataset!$A10) -> 1 | I10: =WEEKDAY(Dataset!$A10) -> 6 | J10: =Dataset!$D10-Dataset!$C10 -> -155
A11: 44207 | B11: Power source | C11: 50 | E11: Gas/Electrics | F11: Living Expenses | G11: Expense | H11: =MONTH(Dataset!$A11) -> 1 | I11: =WEEKDAY(Dataset!$A11) -> 2 | J11: =Dataset!$D11-Dataset!$C11 -> -50
A12: 44207 | B12: Drink | C12: 5 | E12: Coffee | F12: Dining Out | G12: Expense | H12: =MONTH(Dataset!$A12) -> 1 | I12: =WEEKDAY(Dataset!$A12) -> 2 | J12: =Dataset!$D12-Dataset!$C12 -> -5
A13: 44208 | B13: Drink | C13: 5 | E13: Coffee | F13: Dining Out | G13: Expense | H13: =MONTH(Dataset!$A13) -> 1 | I13: =WEEKDAY(Dataset!$A13) -> 3 | J13: =Dataset!$D13-Dataset!$C13 -> -5
A14: 44209 | B14: Fuel | C14: 77 | E14: Coffee | F14: Dining Out | G14: Expense | H14: =MONTH(Dataset!$A14) -> 1 | I14: =WEEKDAY(Dataset!$A14) -> 4 | J14: =Dataset!$D14-Dataset!$C14 -> -77
... A23: 44213 | B23: Uba | C23: 28 | E23: Taxi | F23: Transport | G23: Expense | H23: =MONTH(Dataset!$A23) -> 1 | I23: =WEEKDAY(Dataset!$A23) -> 1 | J23: =Dataset!$D23-Dataset!$C23 -> -28
A24: 44214 | B24: Onlne earning | D24: 4500 | E24: YouTube | F24: Passive | G24: Income | H24: =MONTH(Dataset!$A24) -> 1 | I24: =WEEKDAY(Dataset!$A24) -> 2 | J24: =Dataset!$D24-Dataset!$C24 -> 4500
A25: 44214 | B25: Drink | C25: 5 | E25: Coffee | F25: Dining Out | G25: Expense | H25: =MONTH(Dataset!$A25) -> 1 | I25: =WEEKDAY(Dataset!$A25) -> 2 | J25: =Dataset!$D25-Dataset!$C25 -> -5
A26: 44215 | B26: Drink | C26: 5 | E26: Coffee | F26: Dining Out | G26: Expense | H26: =MONTH(Dataset!$A26) -> 1 | I26: =WEEKDAY(Dataset!$A26) -> 3 | J26: =Dataset!$D26-Dataset!$C26 -> -5
A27: 44215 | B27: Onlne earning | D27: 4500 | E27: Teachable | F27: Passive | G27: Income | H27: =MONTH(Dataset!$A27) -> 1 | I27: =WEEKDAY(Dataset!$A27) -> 3 | J27: =Dataset!$D27-Dataset!$C27 -> 4500
A28: 44215 | B28: Phone | C28: 40 | E28: Phone | F28: Living Expenses | G28: Expense | H28: =MONTH(Dataset!$A28) -> 1 | I28: =WEEKDAY(Dataset!$A28) -> 3 | J28: =Dataset!$D28-Dataset!$C28 -> -40
A29: 44216 | B29: Sallah give away | C29: 45 | E29: Gifts | F29: Discretionary | G29: Expense | H29: =MONTH(Dataset!$A29) -> 1 | I29: =WEEKDAY(Dataset!$A29) -> 4 | J29: =Dataset!$D29-Dataset!$C29 -> -45
A30: 44216 | B30: Online streaming | C30: 32 | E30: Entertainment | F30: Discretionary | G30: Expense | H30: =MONTH(Dataset!$A30) -> 1 | I30: =WEEKDAY(Dataset!$A30) -> 4 | J30: =Dataset!$D30-Dataset!$C30 -> -32
A31: 44216 | B31: Drink | C31: 5 | E31: Coffee | F31: Dining Out | G31: Expense | H31: =MONTH(Dataset!$A31) -> 1 | I31: =WEEKDAY(Dataset!$A31) -> 4 | J31: =Dataset!$D31-Dataset!$C31 -> -5
A32: 44217 | B32: Drink | C32: 5 | E32: Coffee | F32: Dining Out | G32: Expense | H32: =MONTH(Dataset!$A32) -> 1 | I32: =WEEKDAY(Dataset!$A32) -> 5 | J32: =Dataset!$D32-Dataset!$C32 -> -5
A33: 44218 | B33: Drink | C33: 5 | E33: Coffee | F33: Dining Out | G33: Expense | H33: =MONTH(Dataset!$A33) -> 1 | I33: =WEEKDAY(Dataset!$A33) -> 6 | J33: =Dataset!$D33-Dataset!$C33 -> -5
A34: 44218 | B34: Green's | C34: 170 | E34: Groceries | F34: Living Expenses | G34: Expense | H34: =MONTH(Dataset!$A34) -> 1 | I34: =WEEKDAY(Dataset!$A34) -> 6 | J34: =Dataset!$D34-Dataset!$C34 -> -170
A35: 44219 | B35: Suya | C35: 37 | E35: Restaurant | F35: Dining Out | G35: Expense | H35: =MONTH(Dataset!$A35) -> 1 | I35: =WEEKDAY(Dataset!$A35) -> 7 | J35: =Dataset!$D35-Dataset!$C35 -> -37
A36: 44220 | B36: Oha soup/White soup | C36: 12 | E36: Restaurant | F36: Dining Out | G36: Expense | H36: =MONTH(Dataset!$A36) -> 1 | I36: =WEEKDAY(Dataset!$A36) -> 1 | J36: =Dataset!$D36-Dataset!$C36 -> -12
A37: 44221 | B37: Orphanage | C37: 55 | E37: Donation | F37: Charity | G37: Expense | H37: =MONTH(Dataset!$A37) -> 1 | I37: =WEEKDAY(Dataset!$A37) -> 2 | J37: =Dataset!$D37-Dataset!$C37 -> -55
A38: 44221 | B38: Fuel | C38: 63 | E38: Fueling | F38: Transport | G38: Expense | H38: =MONTH(Dataset!$A38) -> 1 | I38: =WEEKDAY(Dataset!$A38) -> 2 | J38: =Dataset!$D38-Dataset!$C38 -> -63
A39: 44221 | B39: Drink | C39: 5 | E39: Coffee | F39: Dining Out | G39: Expense | H39: =MONTH(Dataset!$A39) -> 1 | I39: =WEEKDAY(Dataset!$A39) -> 2 | J39: =Dataset!$D39-Dataset!$C39 -> -5
... A48: 44227 | B48: Uba | C48: 23 | E48: Taxi | F48: Transport | G48: Expense | H48: =MONTH(Dataset!$A48) -> 1 | I48: =WEEKDAY(Dataset!$A48) -> 1 | J48: =Dataset!$D48-Dataset!$C48 -> -23
A49: 44228 | B49: Data With Decision | D49: 5000 | E49: Data with Decision | F49: Salary | G49: Income | H49: =MONTH(Dataset!$A49) -> 2 | I49: =WEEKDAY(Dataset!$A49) -> 2 | J49: =Dataset!$D49-Dataset!$C49 -> 5000
A50: 44228 | B50: Drink | C50: 5 | E50: Coffee | F50: Dining Out | G50: Expense | H50: =MONTH(Dataset!$A50) -> 2 | I50: =WEEKDAY(Dataset!$A50) -> 2 | J50: =Dataset!$D50-Dataset!$C50 -> -5
A51: 44229 | B51: Estate Mangement | C51: 900 | E51: Rent | F51: Living Expenses | G51: Expense | H51: =MONTH(Dataset!$A51) -> 2 | I51: =WEEKDAY(Dataset!$A51) -> 3 | J51: =Dataset!$D51-Dataset!$C51 -> -900
A52: 44229 | B52: Financail upgrade | C52: 150 | E52: Cash loan | F52: Transport | G52: Expense | H52: =MONTH(Dataset!$A52) -> 2 | I52: =WEEKDAY(Dataset!$A52) -> 3 | J52: =Dataset!$D52-Dataset!$C52 -> -150
A53: 44229 | B53: Drink | C53: 5 | E53: Coffee | F53: Dining Out | G53: Expense | H53: =MONTH(Dataset!$A53) -> 2 | I53: =WEEKDAY(Dataset!$A53) -> 3 | J53: =Dataset!$D53-Dataset!$C53 -> -5
A54: 44230 | B54: Drink | C54: 5 | E54: Coffee | F54: Dining Out | G54: Expense | H54: =MONTH(Dataset!$A54) -> 2 | I54: =WEEKDAY(Dataset!$A54) -> 4 | J54: =Dataset!$D54-Dataset!$C54 -> -5
A55: 44231 | B55: Drink | C55: 5 | E55: Coffee | F55: Dining Out | G55: Expense | H55: =MONTH(Dataset!$A55) -> 2 | I55: =WEEKDAY(Dataset!$A55) -> 5 | J55: =Dataset!$D55-Dataset!$C55 -> -5
A56: 44232 | B56: Drink | C56: 5 | E56: Coffee | F56: Dining Out | G56: Expense | H56: =MONTH(Dataset!$A56) -> 2 | I56: =WEEKDAY(Dataset!$A56) -> 6 | J56: =Dataset!$D56-Dataset!$C56 -> -5
A57: 44232 | B57: Green's | C57: 205 | E57: Groceries | F57: Living Expenses | G57: Expense | H57: =MONTH(Dataset!$A57) -> 2 | I57: =WEEKDAY(Dataset!$A57) -> 6 | J57: =Dataset!$D57-Dataset!$C57 -> -205
A58: 44235 | B58: Power source | C58: 51.1 | E58: Gas/Electrics | F58: Living Expenses | G58: Expense | H58: =MONTH(Dataset!$A58) -> 2 | I58: =WEEKDAY(Dataset!$A58) -> 2 | J58: =Dataset!$D58-Dataset!$C58 -> -51.1
A59: 44235 | B59: Drink | C59: 5 | E59: Coffee | F59: Dining Out | G59: Expense | H59: =MONTH(Dataset!$A59) -> 2 | I59: =WEEKDAY(Dataset!$A59) -> 2 | J59: =Dataset!$D59-Dataset!$C59 -> -5
A60: 44236 | B60: Drink | C60: 5 | E60: Coffee | F60: Dining Out | G60: Expense | H60: =MONTH(Dataset!$A60) -> 2 | I60: =WEEKDAY(Dataset!$A60) -> 3 | J60: =Dataset!$D60-Dataset!$C60 -> -5
A61: 44237 | B61: Fuel | C61: 78 | E61: Fueling | F61: Transport | G61: Expense | H61: =MONTH(Dataset!$A61) -> 2 | I61: =WEEKDAY(Dataset!$A61) -> 4 | J61: =Dataset!$D61-Dataset!$C61 -> -78
... A70: 44241 | B70: Uba | C70: 28.9 | E70: Taxi | F70: Transport | G70: Expense | H70: =MONTH(Dataset!$A70) -> 2 | I70: =WEEKDAY(Dataset!$A70) -> 1 | J70: =Dataset!$D70-Dataset!$C70 -> -28.9
A71: 44242 | B71: Onlne earning | D71: 800 | E71: YouTube | F71: Passive | G71: Income | H71: =MONTH(Dataset!$A71) -> 2 | I71: =WEEKDAY(Dataset!$A71) -> 2 | J71: =Dataset!$D71-Dataset!$C71 -> 800
A72: 44242 | B72: Drink | C72: 5 | E72: Coffee | F72: Dining Out | G72: Expense | H72: =MONTH(Dataset!$A72) -> 2 | I72: =WEEKDAY(Dataset!$A72) -> 2 | J72: =Dataset!$D72-Dataset!$C72 -> -5
A73: 44243 | B73: Drink | C73: 5 | E73: Coffee | F73: Dining Out | G73: Expense | H73: =MONTH(Dataset!$A73) -> 2 | I73: =WEEKDAY(Dataset!$A73) -> 3 | J73: =Dataset!$D73-Dataset!$C73 -> -5
A74: 44243 | B74: Phone | C74: 40 | E74: Phone | F74: Living Expenses | G74: Expense | H74: =MONTH(Dataset!$A74) -> 2 | I74: =WEEKDAY(Dataset!$A74) -> 3 | J74: =Dataset!$D74-Dataset!$C74 -> -40
A75: 44244 | B75: Sallah give away | C75: 45.9 | E75: Gifts | F75: Discretionary | G75: Expense | H75: =MONTH(Dataset!$A75) -> 2 | I75: =WEEKDAY(Dataset!$A75) -> 4 | J75: =Dataset!$D75-Dataset!$C75 -> -45.9
A76: 44244 | B76: Online streaming | C76: 35 | E76: Entertainment | F76: Discretionary | G76: Expense | H76: =MONTH(Dataset!$A76) -> 2 | I76: =WEEKDAY(Dataset!$A76) -> 4 | J76: =Dataset!$D76-Dataset!$C76 -> -35
A77: 44244 | B77: Drink | C77: 5 | E77: Coffee | F77: Dining Out | G77: Expense | H77: =MONTH(Dataset!$A77) -> 2 | I77: =WEEKDAY(Dataset!$A77) -> 4 | J77: =Dataset!$D77-Dataset!$C77 -> -5
A78: 44245 | B78: Drink | C78: 5 | E78: Coffee | F78: Dining Out | G78: Expense | H78: =MONTH(Dataset!$A78) -> 2 | I78: =WEEKDAY(Dataset!$A78) -> 5 | J78: =Dataset!$D78-Dataset!$C78 -> -5
A79: 44246 | B79: Drink | C79: 5 | E79: Coffee | F79: Dining Out | G79: Expense | H79: =MONTH(Dataset!$A79) -> 2 | I79: =WEEKDAY(Dataset!$A79) -> 6 | J79: =Dataset!$D79-Dataset!$C79 -> -5
A80: 44246 | B80: Green's | C80: 171 | E80: Groceries | F80: Living Expenses | G80: Expense | H80: =MONTH(Dataset!$A80) -> 2 | I80: =WEEKDAY(Dataset!$A80) -> 6 | J80: =Dataset!$D80-Dataset!$C80 -> -171
A81: 44247 | B81: Suya | C81: 37.9 | E81: Restaurant | F81: Dining Out | G81: Expense | H81: =MONTH(Dataset!$A81) -> 2 | I81: =WEEKDAY(Dataset!$A81) -> 7 | J81: =Dataset!$D81-Dataset!$C81 -> -37.9
A82: 44248 | B82: Oha soup/White soup | C82: 12.9 | E82: Restaurant | F82: Dining Out | G82: Expense | H82: =MONTH(Dataset!$A82) -> 2 | I82: =WEEKDAY(Dataset!$A82) -> 1 | J82: =Dataset!$D82-Dataset!$C82 -> -12.9
A83: 44249 | B83: Orphanage | C83: 55 | E83: Donation | F83: Charity | G83: Expense | H83: =MONTH(Dataset!$A83) -> 2 | I83: =WEEKDAY(Dataset!$A83) -> 2 | J83: =Dataset!$D83-Dataset!$C83 -> -55
... A94: 44255 | B94: Uba | C94: 24.1 | E94: Taxi | F94: Transport | G94: Expense | H94: =MONTH(Dataset!$A94) -> 2 | I94: =WEEKDAY(Dataset!$A94) -> 1 | J94: =Dataset!$D94-Dataset!$C94 -> -24.1
A95: 44256 | B95: Data With Decision | D95: 5000 | E95: Data with Decision | F95: Salary | G95: Income | H95: =MONTH(Dataset!$A95) -> 3 | I95: =WEEKDAY(Dataset!$A95) -> 2 | J95: =Dataset!$D95-Dataset!$C95 -> 5000
A96: 44256 | B96: Drink | C96: 5 | E96: Coffee | F96: Dining Out | G96: Expense | H96: =MONTH(Dataset!$A96) -> 3 | I96: =WEEKDAY(Dataset!$A96) -> 2 | J96: =Dataset!$D96-Dataset!$C96 -> -5
A97: 44257 | B97: Estate Mangement | C97: 900 | E97: Rent | F97: Living Expenses | G97: Expense | H97: =MONTH(Dataset!$A97) -> 3 | I97: =WEEKDAY(Dataset!$A97) -> 3 | J97: =Dataset!$D97-Dataset!$C97 -> -900
A98: 44257 | B98: Financail upgrade | C98: 150 | E98: Cash loan | F98: Transport | G98: Expense | H98: =MONTH(Dataset!$A98) -> 3 | I98: =WEEKDAY(Dataset!$A98) -> 3 | J98: =Dataset!$D98-Dataset!$C98 -> -150
A99: 44257 | B99: Drink | C99: 5 | E99: Coffee | F99: Dining Out | G99: Expense | H99: =MONTH(Dataset!$A99) -> 3 | I99: =WEEKDAY(Dataset!$A99) -> 3 | J99: =Dataset!$D99-Dataset!$C99 -> -5
A100: 44258 | B100: Drink | C100: 5 | E100: Coffee | F100: Dining Out | G100: Expense | H100: =MONTH(Dataset!$A100) -> 3 | I100: =WEEKDAY(Dataset!$A100) -> 4 | J100: =Dataset!$D100-Dataset!$C100 -> -5
A101: 44259 | B101: Drink | C101: 5 | E101: Coffee | F101: Dining Out | G101: Expense | H101: =MONTH(Dataset!$A101) -> 3 | I101: =WEEKDAY(Dataset!$A101) -> 5 | J101: =Dataset!$D101-Dataset!$C101 -> -5
A102: 44260 | B102: Drink | C102: 5 | E102: Coffee | F102: Dining Out | G102: Expense | H102: =MONTH(Dataset!$A102) -> 3 | I102: =WEEKDAY(Dataset!$A102) -> 6 | J102: =Dataset!$D102-Dataset!$C102 -> -5
A103: 44260 | B103: Green's | C103: 149 | E103: Groceries | F103: Living Expenses | G103: Expense | H103: =MONTH(Dataset!$A103) -> 3 | I103: =WEEKDAY(Dataset!$A103) -> 6 | J103: =Dataset!$D103-Dataset!$C103 -> -149
A104: 44263 | B104: Power source | C104: 52.1 | E104: Gas/Electrics | F104: Living Expenses | G104: Expense | H104: =MONTH(Dataset!$A104) -> 3 | I104: =WEEKDAY(Dataset!$A104) -> 2 | J104: =Dataset!$D104-Dataset!$C104 -> -52.1
A105: 44263 | B105: Drink | C105: 5 | E105: Coffee | F105: Dining Out | G105: Expense | H105: =MONTH(Dataset!$A105) -> 3 | I105: =WEEKDAY(Dataset!$A105) -> 2 | J105: =Dataset!$D105-Dataset!$C105 -> -5
A106: 44264 | B106: Drink | C106: 5 | E106: Coffee | F106: Dining Out | G106: Expense | H106: =MONTH(Dataset!$A106) -> 3 | I106: =WEEKDAY(Dataset!$A106) -> 3 | J106: =Dataset!$D106-Dataset!$C106 -> -5
A107: 44265 | B107: Fuel | C107: 78.9 | E107: Fueling | F107: Transport | G107: Expense | H107: =MONTH(Dataset!$A107) -> 3 | I107: =WEEKDAY(Dataset!$A107) -> 4 | J107: =Dataset!$D107-Dataset!$C107 -> -78.9
... A116: 44269 | B116: Uba | C116: 30 | E116: Taxi | F116: Transport | G116: Expense | H116: =MONTH(Dataset!$A116) -> 3 | I116: =WEEKDAY(Dataset!$A116) -> 1 | J116: =Dataset!$D116-Dataset!$C116 -> -30
A117: 44270 | B117: Onlne earning | D117: 1000 | E117: YouTube | F117: Passive | G117: Income | H117: =MONTH(Dataset!$A117) -> 3 | I117: =WEEKDAY(Dataset!$A117) -> 2 | J117: =Dataset!$D117-Dataset!$C117 -> 1000
A118: 44270 | B118: Drink | C118: 5 | E118: Coffee | F118: Dining Out | G118: Expense | H118: =MONTH(Dataset!$A118) -> 3 | I118: =WEEKDAY(Dataset!$A118) -> 2 | J118: =Dataset!$D118-Dataset!$C118 -> -5
A119: 44271 | B119: Drink | C119: 5 | E119: Coffee | F119: Dining Out | G119: Expense | H119: =MONTH(Dataset!$A119) -> 3 | I119: =WEEKDAY(Dataset!$A119) -> 3 | J119: =Dataset!$D119-Dataset!$C119 -> -5
A120: 44271 | B120: Taken medication | C120: 75 | E120: Doctor | F120: Medical | G120: Expense | H120: =MONTH(Dataset!$A120) -> 3 | I120: =WEEKDAY(Dataset!$A120) -> 3 | J120: =Dataset!$D120-Dataset!$C120 -> -75
A121: 44271 | B121: Phone | C121: 40 | E121: Phone | F121: Living Expenses | G121: Expense | H121: =MONTH(Dataset!$A121) -> 3 | I121: =WEEKDAY(Dataset!$A121) -> 3 | J121: =Dataset!$D121-Dataset!$C121 -> -40
A122: 44272 | B122: Sallah give away | C122: 46.8 | E122: Gifts | F122: Discretionary | G122: Expense | H122: =MONTH(Dataset!$A122) -> 3 | I122: =WEEKDAY(Dataset!$A122) -> 4 | J122: =Dataset!$D122-Dataset!$C122 -> -46.8
A123: 44272 | B123: Online streaming | C123: 35 | E123: Entertainment | F123: Discretionary | G123: Expense | H123: =MONTH(Dataset!$A123) -> 3 | I123: =WEEKDAY(Dataset!$A123) -> 4 | J123: =Dataset!$D123-Dataset!$C123 -> -35
A124: 44272 | B124: Drink | C124: 5 | E124: Coffee | F124: Dining Out | G124: Expense | H124: =MONTH(Dataset!$A124) -> 3 | I124: =WEEKDAY(Dataset!$A124) -> 4 | J124: =Dataset!$D124-Dataset!$C124 -> -5
A125: 44273 | B125: Drink | C125: 5 | E125: Coffee | F125: Dining Out | G125: Expense | H125: =MONTH(Dataset!$A125) -> 3 | I125: =WEEKDAY(Dataset!$A125) -> 5 | J125: =Dataset!$D125-Dataset!$C125 -> -5
A126: 44274 | B126: Drink | C126: 5 | E126: Coffee | F126: Dining Out | G126: Expense | H126: =MONTH(Dataset!$A126) -> 3 | I126: =WEEKDAY(Dataset!$A126) -> 6 | J126: =Dataset!$D126-Dataset!$C126 -> -5
A127: 44274 | B127: Green's | C127: 171.9 | E127: Groceries | F127: Living Expenses | G127: Expense | H127: =MONTH(Dataset!$A127) -> 3 | I127: =WEEKDAY(Dataset!$A127) -> 6 | J127: =Dataset!$D127-Dataset!$C127 -> -171.9
A128: 44275 | B128: Suya | C128: 39 | E128: Restaurant | F128: Dining Out | G128: Expense | H128: =MONTH(Dataset!$A128) -> 3 | I128: =WEEKDAY(Dataset!$A128) -> 7 | J128: =Dataset!$D128-Dataset!$C128 -> -39
A129: 44276 | B129: Oha soup/White soup | C129: 14 | E129: Restaurant | F129: Dining Out | G129: Expense | H129: =MONTH(Dataset!$A129) -> 3 | I129: =WEEKDAY(Dataset!$A129) -> 1 | J129: =Dataset!$D129-Dataset!$C129 -> -14
... A144: 44286 | B144: Drink | C144: 5 | E144: Coffee | F144: Dining Out | G144: Expense | H144: =MONTH(Dataset!$A144) -> 3 | I144: =WEEKDAY(Dataset!$A144) -> 4 | J144: =Dataset!$D144-Dataset!$C144 -> -5
A145: 44287 | B145: Data With Decision | D145: 5000 | E145: Data with Decision | F145: Salary | G145: Income | H145: =MONTH(Dataset!$A145) -> 4 | I145: =WEEKDAY(Dataset!$A145) -> 5 | J145: =Dataset!$D145-Dataset!$C145 -> 5000
A146: 44287 | B146: Drink | C146: 5 | E146: Coffee | F146: Dining Out | G146: Expense | H146: =MONTH(Dataset!$A146) -> 4 | I146: =WEEKDAY(Dataset!$A146) -> 5 | J146: =Dataset!$D146-Dataset!$C146 -> -5
A147: 44288 | B147: Estate Mangement | C147: 900 | E147: Rent | F147: Living Expenses | G147: Expense | H147: =MONTH(Dataset!$A147) -> 4 | I147: =WEEKDAY(Dataset!$A147) -> 6 | J147: =Dataset!$D147-Dataset!$C147 -> -900
A148: 44288 | B148: Financail upgrade | C148: 150 | E148: Cash loan | F148: Transport | G148: Expense | H148: =MONTH(Dataset!$A148) -> 4 | I148: =WEEKDAY(Dataset!$A148) -> 6 | J148: =Dataset!$D148-Dataset!$C148 -> -150
A149: 44288 | B149: Drink | C149: 5 | E149: Coffee | F149: Dining Out | G149: Expense | H149: =MONTH(Dataset!$A149) -> 4 | I149: =WEEKDAY(Dataset!$A149) -> 6 | J149: =Dataset!$D149-Dataset!$C149 -> -5
A150: 44289 | B150: Drink | C150: 5 | E150: Coffee | F150: Dining Out | G150: Expense | H150: =MONTH(Dataset!$A150) -> 4 | I150: =WEEKDAY(Dataset!$A150) -> 7 | J150: =Dataset!$D150-Dataset!$C150 -> -5
A151: 44290 | B151: Drink | C151: 5 | E151: Coffee | F151: Dining Out | G151: Expense | H151: =MONTH(Dataset!$A151) -> 4 | I151: =WEEKDAY(Dataset!$A151) -> 1 | J151: =Dataset!$D151-Dataset!$C151 -> -5
A152: 44291 | B152: Drink | C152: 5 | E152: Coffee | F152: Dining Out | G152: Expense | H152: =MONTH(Dataset!$A152) -> 4 | I152: =WEEKDAY(Dataset!$A152) -> 2 | J152: =Dataset!$D152-Dataset!$C152 -> -5
A153: 44291 | B153: Green's | C153: 158.2 | E153: Groceries | F153: Living Expenses | G153: Expense | H153: =MONTH(Dataset!$A153) -> 4 | I153: =WEEKDAY(Dataset!$A153) -> 2 | J153: =Dataset!$D153-Dataset!$C153 -> -158.2
A154: 44294 | B154: Power source | C154: 53.2 | E154: Gas/Electrics | F154: Living Expenses | G154: Expense | H154: =MONTH(Dataset!$A154) -> 4 | I154: =WEEKDAY(Dataset!$A154) -> 5 | J154: =Dataset!$D154-Dataset!$C154 -> -53.2
A155: 44294 | B155: Drink | C155: 5 | E155: Coffee | F155: Dining Out | G155: Expense | H155: =MONTH(Dataset!$A155) -> 4 | I155: =WEEKDAY(Dataset!$A155) -> 5 | J155: =Dataset!$D155-Dataset!$C155 -> -5
A156: 44295 | B156: Drink | C156: 5 | E156: Coffee | F156: Dining Out | G156: Expense | H156: =MONTH(Dataset!$A156) -> 4 | I156: =WEEKDAY(Dataset!$A156) -> 6 | J156: =Dataset!$D156-Dataset!$C156 -> -5
...

Sheet Clean data
A1: Date | B1: Year | C1: Description | D1: Sub-category | E1: Category | F1: Main-Category | G1: Amount | H1: Payment_mode | I1: Income | J1: Expense | K1: Net_balance | L1: Budget_status
A2: 44200 | B2: 2021 | C2: Data With Decision | D2: Data with Decision | E2: Salary | F2: Salary | G2: 5000 | H2: Bank Credit | I2: 5000 | J2: 0 | K2: 5000 | L2: Saving
A3: 44200 | B3: 2021 | C3: Drink | D3: Coffee | E3: Dining Out | F3: Food | G3: -5 | H3: Net Banking | I3: 0 | J3: 5 | K3: -5 | L3: Spenting
A4: 44201 | B4: 2021 | C4: Estate Mangement | D4: Rent | E4: Living Expenses | F4: Housing | G4: -900 | H4: Bank Transfer | I4: 0 | J4: 900 | K4: -900 | L4: Spenting
A5: 44201 | B5: 2021 | C5: Financail upgrade | D5: Cash loan | E5: Transport | F5: Loan | G5: -150 | H5: Cash | I5: 0 | J5: 150 | K5: -150 | L5: Spenting
A6: 44201 | B6: 2021 | C6: Drink | D6: Coffee | E6: Dining Out | F6: Food | G6: -5 | H6: Net Banking | I6: 0 | J6: 5 | K6: -5 | L6: Spenting
A7: 44202 | B7: 2021 | C7: Drink | D7: Coffee | E7: Dining Out | F7: Food | G7: -5 | H7: Net Banking | I7: 0 | J7: 5 | K7: -5 | L7: Spenting
A8: 44203 | B8: 2021 | C8: Drink | D8: Coffee | E8: Dining Out | F8: Food | G8: -5 | H8: Net Banking | I8: 0 | J8: 5 | K8: -5 | L8: Spenting
A9: 44204 | B9: 2021 | C9: Drink | D9: Coffee | E9: Dining Out | F9: Food | G9: -5 | H9: Net Banking | I9: 0 | J9: 5 | K9: -5 | L9: Spenting
A10: 44204 | B10: 2021 | C10: Green's | D10: Groceries | E10: Living Expenses | F10: Food | G10: -155 | H10: Net Banking | I10: 0 | J10: 155 | K10: -155 | L10: Spenting
A11: 44207 | B11: 2021 | C11: Power source | D11: Gas/Electrics | E11: Living Expenses | F11: Food | G11: -50 | H11: Net Banking | I11: 0 | J11: 50 | K11: -50 | L11: Spenting
A12: 44207 | B12: 2021 | C12: Drink | D12: Coffee | E12: Dining Out | F12: Food | G12: -5 | H12: Net Banking | I12: 0 | J12: 5 | K12: -5 | L12: Spenting
A13: 44208 | B13: 2021 | C13: Drink | D13: Coffee | E13: Dining Out | F13: Food | G13: -5 | H13: Net Banking | I13: 0 | J13: 5 | K13: -5 | L13: Spenting
... A487: 44500 | B487: 2021 | C487: Foodary | D487: Restaurant | E487: Dining Out | F487: Food | G487: -15 | H487: Net Banking | I487: 0 | J487: 15 | K487: -15 | L487: Spenting

Sheet Dim_table
A1: Main-Category | B1: Sub-category | C1: Category_ID | D1: Category_Type
A2: Salary | B2: Data with Decision | C2: =IF(A2="Salary","SAL-001", IF(A2="Housing","HOU-002", IF(A2="Food","FOO-003", IF(A2="Transportation","TRA-004", IF(A2="Utilities","UTI-005", IF(A2="Entertainment","ENT-006", IF(A2="Medical","MED-007", IF(A2="Personal","PER-008", IF(A2="Loan","LOA-009","PVE-010"))))))))) -> SAL-001 | D2: =IF(OR(A2="Salary",A2="Passive"),"Income","Expense") -> Income
A3: Food | B3: Coffee | C3: =IF(A3="Salary","SAL-001", IF(A3="Housing","HOU-002", IF(A3="Food","FOO-003", IF(A3="Transportation","TRA-004", IF(A3="Utilities","UTI-005", IF(A3="Entertainment","ENT-006", IF(A3="Medical","MED-007", IF(A3="Personal","PER-008", IF(A3="Loan","LOA-009","PVE-010"))))))))) -> FOO-003 | D3: =IF(OR(A3="Salary",A3="Passive"),"Income","Expense") -> Expense
A4: Housing | B4: Rent | C4: =IF(A4="Salary","SAL-001", IF(A4="Housing","HOU-002", IF(A4="Food","FOO-003", IF(A4="Transportation","TRA-004", IF(A4="Utilities","UTI-005", IF(A4="Entertainment","ENT-006", IF(A4="Medical","MED-007", IF(A4="Personal","PER-008", IF(A4="Loan","LOA-009","PVE-010"))))))))) -> HOU-002 | D4: =IF(OR(A4="Salary",A4="Passive"),"Income","Expense") -> Expense
A5: Loan | B5: Cash loan | C5: =IF(A5="Salary","SAL-001", IF(A5="Housing","HOU-002", IF(A5="Food","FOO-003", IF(A5="Transportation","TRA-004", IF(A5="Utilities","UTI-005", IF(A5="Entertainment","ENT-006", IF(A5="Medical","MED-007", IF(A5="Personal","PER-008", IF(A5="Loan","LOA-009","PVE-010"))))))))) -> LOA-009 | D5: =IF(OR(A5="Salary",A5="Passive"),"Income","Expense") -> Expense
A6: Food | B6: Coffee | C6: =IF(A6="Salary","SAL-001", IF(A6="Housing","HOU-002", IF(A6="Food","FOO-003", IF(A6="Transportation","TRA-004", IF(A6="Utilities","UTI-005", IF(A6="Entertainment","ENT-006", IF(A6="Medical","MED-007", IF(A6="Personal","PER-008", IF(A6="Loan","LOA-009","PVE-010"))))))))) -> FOO-003 | D6: =IF(OR(A6="Salary",A6="Passive"),"Income","Expense") -> Expense
A7: Food | B7: Coffee | C7: =IF(A7="Salary","SAL-001", IF(A7="Housing","HOU-002", IF(A7="Food","FOO-003", IF(A7="Transportation","TRA-004", IF(A7="Utilities","UTI-005", IF(A7="Entertainment","ENT-006", IF(A7="Medical","MED-007", IF(A7="Personal","PER-008", IF(A7="Loan","LOA-009","PVE-010"))))))))) -> FOO-003 | D7: =IF(OR(A7="Salary",A7="Passive"),"Income","Expense") -> Expense
A8: Food | B8: Coffee | C8: =IF(A8="Salary","SAL-001", IF(A8="Housing","HOU-002", IF(A8="Food","FOO-003", IF(A8="Transportation","TRA-004", IF(A8="Utilities","UTI-005", IF(A8="Entertainment","ENT-006", IF(A8="Medical","MED-007", IF(A8="Personal","PER-008", IF(A8="Loan","LOA-009","PVE-010"))))))))) -> FOO-003 | D8: =IF(OR(A8="Salary",A8="Passive"),"Income","Expense") -> Expense
A9: Food | B9: Coffee | C9: =IF(A9="Salary","SAL-001", IF(A9="Housing","HOU-002", IF(A9="Food","FOO-003", IF(A9="Transportation","TRA-004", IF(A9="Utilities","UTI-005", IF(A9="Entertainment","ENT-006", IF(A9="Medical","MED-007", IF(A9="Personal","PER-008", IF(A9="Loan","LOA-009","PVE-010"))))))))) -> FOO-003 | D9: =IF(OR(A9="Salary",A9="Passive"),"Income","Expense") -> Expense
A10: Food | B10: Groceries | C10: =IF(A10="Salary","SAL-001", IF(A10="Housing","HOU-002", IF(A10="Food","FOO-003", IF(A10="Transportation","TRA-004", IF(A10="Utilities","UTI-005", IF(A10="Entertainment","ENT-006", IF(A10="Medical","MED-007", IF(A10="Personal","PER-008", IF(A10="Loan","LOA-009","PVE-010"))))))))) -> FOO-003 | D10: =IF(OR(A10="Salary",A10="Passive"),"Income","Expense") -> Expense
A11: Food | B11: Gas/Electrics | C11: =IF(A11="Salary","SAL-001", IF(A11="Housing","HOU-002", IF(A11="Food","FOO-003", IF(A11="Transportation","TRA-004", IF(A11="Utilities","UTI-005", IF(A11="Entertainment","ENT-006", IF(A11="Medical","MED-007", IF(A11="Personal","PER-008", IF(A11="Loan","LOA-009","PVE-010"))))))))) -> FOO-003 | D11: =IF(OR(A11="Salary",A11="Passive"),"Income","Expense") -> Expense
A12: Food | B12: Coffee | C12: =IF(A12="Salary","SAL-001", IF(A12="Housing","HOU-002", IF(A12="Food","FOO-003", IF(A12="Transportation","TRA-004", IF(A12="Utilities","UTI-005", IF(A12="Entertainment","ENT-006", IF(A12="Medical","MED-007", IF(A12="Personal","PER-008", IF(A12="Loan","LOA-009","PVE-010"))))))))) -> FOO-003 | D12: =IF(OR(A12="Salary",A12="Passive"),"Income","Expense") -> Expense
A13: Food | B13: Coffee | C13: =IF(A13="Salary","SAL-001", IF(A13="Housing","HOU-002", IF(A13="Food","FOO-003", IF(A13="Transportation","TRA-004", IF(A13="Utilities","UTI-005", IF(A13="Entertainment","ENT-006", IF(A13="Medical","MED-007", IF(A13="Personal","PER-008", IF(A13="Loan","LOA-009","PVE-010"))))))))) -> FOO-003 | D13: =IF(OR(A13="Salary",A13="Passive"),"Income","Expense") -> Expense
... A487: Food | B487: Restaurant | C487: =IF(A487="Salary","SAL-001", IF(A487="Housing","HOU-002", IF(A487="Food","FOO-003", IF(A487="Transportation","TRA-004", IF(A487="Utilities","UTI-005", IF(A487="Entertainment","ENT-006", IF(A487="Medical","MED-007", IF(A487="Personal","PER-008", IF(A487="Loan","LOA-009","PVE-010"))))))))) -> FOO-003 | D487: =IF(OR(A487="Salary",A487="Passive"),"Income","Expense") -> Expense

Sheet Fact_table
A1: Date | B1: Category_ID | C1: Amount
A2: 44200 | B2: =VLOOKUP('Clean data'!F:F,Dim_table!A:C,3,FALSE) -> SAL-001 | C2: 5000
A3: 44200 | B3: =VLOOKUP('Clean data'!F:F,Dim_table!A:C,3,FALSE) -> FOO-003 | C3: -5
A4: 44201 | B4: =VLOOKUP('Clean data'!F:F,Dim_table!A:C,3,FALSE) -> HOU-002 | C4: -900
A5: 44201 | B5: =VLOOKUP('Clean data'!F:F,Dim_table!A:C,3,FALSE) -> LOA-009 | C5: -150
A6: 44201 | B6: =VLOOKUP('Clean data'!F:F,Dim_table!A:C,3,FALSE) -> FOO-003 | C6: -5
A7: 44202 | B7: =VLOOKUP('Clean data'!F:F,Dim_table!A:C,3,FALSE) -> FOO-003 | C7: -5
A8: 44203 | B8: =VLOOKUP('Clean data'!F:F,Dim_table!A:C,3,FALSE) -> FOO-003 | C8: -5
A9: 44204 | B9: =VLOOKUP('Clean data'!F:F,Dim_table!A:C,3,FALSE) -> FOO-003 | C9: -5
A10: 44204 | B10: =VLOOKUP('Clean data'!F:F,Dim_table!A:C,3,FALSE) -> FOO-003 | C10: -155
A11: 44207 | B11: =VLOOKUP('Clean data'!F:F,Dim_table!A:C,3,FALSE) -> FOO-003 | C11: -50
A12: 44207 | B12: =VLOOKUP('Clean data'!F:F,Dim_table!A:C,3,FALSE) -> FOO-003 | C12: -5
A13: 44208 | B13: =VLOOKUP('Clean data'!F:F,Dim_table!A:C,3,FALSE) -> FOO-003 | C13: -5
... A487: 44500 | B487: =VLOOKUP('Clean data'!F:F,Dim_table!A:C,3,FALSE) -> FOO-003 | C487: -15

Sheet Pivot
A2: Row Labels | B2: Sum of Income | C2: Sum of Expense
A3: 2021 | B3: 65440 | C3: 30191
A4: Grand Total | B4: 65440 | C4: 30191
A17: Row Labels | B17: Sum of Expense
A18: Jan | B18: 2874
A19: Feb | B19: 2904.6
A20: Mar | B20: 3049.7
A21: Apr | B21: 3038
A22: May | B22: 3116.1
A23: Jun | B23: 3005.7
A24: Jul | B24: 3065
A25: Aug | B25: 2952.1
A26: Sep | B26: 3087.1
A27: Oct | B27: 3098.7
A28: Grand Total | B28: 30191
A34: Row Labels | B34: Sum of Expense
A35: Entertainment | B35: 0.06003776
A36: Food | B36: 0.31379219
A37: Housing | B37: 0.31189427
A38: Loan | B38: 0.049683681
A39: Medical | B39: 0.0074525521
A40: Passive | B40: 0
A41: Personal | B41: 0.17715876
A42: Salary | B42: 0
A43: Transportation | B43: 0.066731807
A44: Utilities | B44: 0.013248981
A45: Grand Total | B45: 1
A52: Row Labels | B52: Count of Payment_mode
A53: Bank Credit | B53: 21
A54: Bank Transfer | B54: 22
A55: Cash | B55: 10
A56: Net Banking | B56: 366
A57: UPI | B57: 67
A58: Grand Total | B58: 486
A70: Row Labels | B70: Average of Amount
A71: Entertainment | B71: -72.504
A72: Food | B72: -30.267412
A73: Housing | B73: -784.7
A74: Loan | B74: -150
A75: Medical | B75: -75
A76: Passive | B76: 1403.6364
A77: Personal | B77: -100.91698
A78: Salary | B78: 5000
A79: Transportation | B79: -51.658974
A80: Utilities | B80: -40
A81: Grand Total | B81: 72.528807

Sheet Dashboard
A1: Dashboard
